{"bestreplyNewsList":[{"newsId":"20160118180917867","url":"http://v.media.daum.net/v/20160118180917867","title":"朴대통령, 입법촉구 1천만 서명 참여..현직 대통령으로 처음(종합2보)","cpKorName":"연합뉴스","summary":"판교역 광장서 서명…\"국회가 역할 제대로 못하니 국민이 바로 잡으려는 것\" \"저도 너무 애가 탔는데, 여러분들 심정이 어떠실지\" (서울=연합뉴스) 이광빈 기자 = 박근혜 대통령은 18일 경제단체와 기업인 등의 주도로 진행 중인 경제활성화 입법촉구를 위한 1천만인 서명 운동에 동참했다. 박 대통령은 이날 판교 차바이오컴플렉스에서 열린 6개 부처 합동업무보고","regDt":"20160118180917","importantYn":"Y","imageUrl":"http://t1.daumcdn.net/news/201601/18/yonhap/20160118180916539geup.jpg","ucccount":5462,"category":"politics"},{"newsId":"20160118115443106","url":"http://v.media.daum.net/v/20160118115443106","title":"朴대통령 \"민생입법 촉구 1000만 서명운동 동참하겠다\"(종합)","cpKorName":"뉴스1","summary":"(서울=뉴스1) 윤태형 기자,유기림 기자 = 박근혜 대통령은 18일 \"어려움에 처한 우리 경제와 커지고 있는 테러 위협을 극복하고자 경제단체와 시민단체를 중심으로 해서 민생 구하기 입법 촉구 1000만인 서명 운동이 시작됐다고 한다\"면서 \"저 역시 국민들과 함께 서명 운동에 동참하겠다\"고 밝혔다. 박 대통령은 이날 오전 경기도 성남시 판교테크노벨리에서 미래","regDt":"20160118115443","importantYn":"Y","imageUrl":"http://t1.daumcdn.net/news/201601/14/NEWS1/20160114160828834dfmr.jpg","ucccount":3933,"category":"politics"},{"newsId":"20160118075504704","url":"http://v.media.daum.net/v/20160118075504704","title":"이재명, \"정부탄압 계속되면 선거 등 국가위임사무 거부 검토\"","cpKorName":"헤럴드경제","summary":"[헤럴드경제=박정규(성남)기자] 이재명 성남시장이 자신의 SNS에 ‘정부탄압이 계속되면 성남시는 국가위임사무 거부를 검토할 것입니다’라는 글을 18일 올렸다. 이 시장은 “성남시는 중앙정부의 재정지원을 안받는 소위 ‘불교부단체’로서 2019년까지 한시적으로 ‘분권교부세’를 87억 정도만 받는 사실상 재정독립단체”라고 밝혔다. 이어 “중앙정부는 독립 지방정부","regDt":"20160118075504","importantYn":"Y","imageUrl":"http://t1.daumcdn.net/news/201601/18/ned/20160118075504169scjk.jpg","ucccount":3429,"category":"society"},{"newsId":"20160118151029267","url":"http://v.media.daum.net/v/20160118151029267","title":"靑 자평 \"어느 정부도 못한 경제민주화 실천\"","cpKorName":"아이뉴스24","summary":"<아이뉴스24> [채송무기자] 청와대가 최근 경제민주화의 상징인 김종인 전 의원이 더불어민주당에 합류하면서 박근혜 정부의 경제민주화에 대해 비판한 것과 관련해 현 정권의 경제민주화 성과 관련 자료를 베포하고 \"역대 어느 정부도 하지 못한 경제민주화를 실천했다\"고 자평했다. 청와대는 18일 자료를 통해 \"과거 어느 정부도 엄두도 내지 못했던 신규순환출자 및","regDt":"20160118151029","importantYn":"Y","imageUrl":"http://t1.daumcdn.net/news/201601/18/inews24/20160118151028157vbev.jpg","ucccount":3091,"category":"politics"},{"newsId":"20160118031904675","url":"http://v.media.daum.net/v/20160118031904675","title":"[단독] 안철수 \"총선서 야권연대 결단코 없을 것\"","cpKorName":"중앙일보","summary":"안철수(얼굴) 국민의당 의원이 4·13 총선을 앞두고 야권 연대를 하지 않겠다고 선언했다. 안 의원은 월간중앙과의 단독 인터뷰에서 “제3의 정당으로서 ‘통합의 지지층’을 확보하겠다”며 “이번 총선에서 야권 연대는 결단코 없을 것”이라고 강조했다. 안 의원과의 인터뷰는 지난 13일 이뤄졌으며 월간중앙 2월호는 18일 발행된다. 　특히 안 의원은 “정치 혁신을","regDt":"20160118031904","importantYn":"Y","imageUrl":"http://t1.daumcdn.net/news/201601/18/joongang/20160118032106390obrs.jpg","ucccount":3074,"category":"politics"},{"newsId":"20160118204405517","url":"http://v.media.daum.net/v/20160118204405517","title":"文, 내일 회견서 대표직 사퇴 천명..김종인에 '원샷' 전권이양(종합)","cpKorName":"연합뉴스","summary":"文측 \"조건 달지 않고 깔끔하게 사퇴 입장 공개천명\" 주중 당무위 의결 거쳐 권한 넘길듯…文 \"선대위가 사실상 비대위\" 김종인, 20일께 선대위 구성안 발표 (서울=연합뉴스) 류지복 기자 = 더불어민주당 문재인 대표가 19일 신년 기자회견에서 대표직 사퇴 방침을 거듭 천명하고 사퇴 수순에 들어갈 것으로 알려졌다. 문 대표 측 핵심 관계자는 18일 연합뉴스","regDt":"20160118204405","importantYn":"Y","imageUrl":"http://t1.daumcdn.net/news/201601/18/yonhap/20160118204403921asvt.jpg","ucccount":2746,"category":"politics"},{"newsId":"20160118104825292","url":"http://v.media.daum.net/v/20160118104825292","title":"세월호 유가족 또 울린 정부..희생자 앞으로 '징병검사 통지서'","cpKorName":"뉴스1","summary":"(서울=뉴스1) 조영빈 기자 = 정부가 세월호 참사로 희생된 단원고 학생의 유가족에게 징병검사통지를 발송한 것으로 밝혀졌다. 이미 큰 상처를 받은 유가족들에게 안이한 행정처리로 또다른 생채기를 안겼다는 지적이 제기된다. 병무청은 18일 \"세월호 유가족에게 지난 6일 '징병검사 일자 및 장소 선택 안내문'을 보내드려 큰 상처를 드리고 가족의 마음을 다시 한번","regDt":"20160118104825","importantYn":"Y","imageUrl":"http://t1.daumcdn.net/news/201508/27/NEWS1/20150827203150004jjln.jpg","ucccount":2501,"category":"politics"},{"newsId":"20160118134820282","url":"http://v.media.daum.net/v/20160118134820282","title":"[일문일답]김무성 \"경제민주화 공약 거의 다 지켜졌다\"","cpKorName":"뉴시스","summary":"【서울=뉴시스】채윤태 기자 = 새누리당 김무성 대표는 \"박근혜 대통령의 경제민주화 공약은 거의 다 지켜졌다\"고 말했다. 김 대표는 18일 오전 국회에서 신년 기자회견을 갖고 \"거의 다 국민에게 한 경제민주화 약속은 지켜지고 있고 앞으로도 노력할 것이며, 부족한 점은 입법할 것\"이라며 이같이 답했다. 그는 경제민주화에 대한 철학을 묻는 질문에 대해 \"지난","regDt":"20160118134820","importantYn":"Y","imageUrl":"http://t1.daumcdn.net/news/201601/18/newsis/20160118120651490ravk.jpg","ucccount":1885,"category":"politics"},{"newsId":"20160118191606757","url":"http://v.media.daum.net/v/20160118191606757","title":"대한항공 조종사 노조 \"연봉 5000만원 올려달라\"","cpKorName":"조선일보","summary":"대한항공 조종사들이 한 번에 연봉을 5000만원 이상 올려줄 것을 요구하며 쟁의 찬반 투표를 벌이고 있다. 최근 확산되는 항공기 조종사들의 몸값 고속 상승이 그 배경에 있다는 분석이다. 대한항공 조종사 노조는 “2015 임금협상 결렬에 따른 쟁의 행위 찬반 투표를 이달 29일까지 진행 중이며 17일 현재 투표율은 54%”라며 “최종 가결될 경우 단계적으로","regDt":"20160118191606","importantYn":"Y","imageUrl":"","ucccount":1724,"category":"economic"},{"newsId":"20160118174903097","url":"http://v.media.daum.net/v/20160118174903097","title":"[덜 떨어지는 국내 유가] 국제유가만큼 떨어졌으면 국내 휘발유값 845원인데..","cpKorName":"한국경제","summary":"[ 조진형/송종현 기자  ] 국내 주유소 휘발유 가격에 대한 소비자들의 불만이 커지고 있다. 국제 유가는 최근 6개월 사이 반토막 아래로 급락했지만 휘발유 값은 크게 떨어지지 않아서다. 이유는 간단하다. 세금 때문이다. 정부는 국제 유가와 관계없이 리터(L)당 900원에 가까운 유류세를 걷어간다. 여기에 정유사와 주유소의 마진(L당 100~150원)을 감안","regDt":"20160118174903","importantYn":"Y","imageUrl":"http://t1.daumcdn.net/news/201601/18/ked/20160118224802745oiwd.jpg","ucccount":1581,"category":"economic"},{"newsId":"20160118210337957","url":"http://v.media.daum.net/v/20160118210337957","title":"\"강제연행의 증거는 없다\"..아베 또 '위안부 뒤집기'","cpKorName":"JTBC","summary":"[앵커] 일본군 위안부 문제에 대한 한일 합의 이후 아베 일본 총리는 이제 마음 놓고 말하는 것 같습니다. 오늘(18일) 또다시 \"위안부 강제연행의 증거는 없다\"고 주장했습니다. 이른바 불가역, 즉 되돌리지 않는다는 조건에 대해 한국 정부는 일본 정부가 과거의 입장으로 되돌아가지 못하게 하기 위해 합의했다고 했지만, 정말 그런가… 의구심이 생기는 대목입니다","regDt":"20160118210337","importantYn":"Y","imageUrl":"http://t1.daumcdn.net/news/201601/18/JTBC/20160118210336090gusa.jpg","ucccount":1439,"category":"politics"},{"newsId":"20160118205009659","url":"http://v.media.daum.net/v/20160118205009659","title":"\"사귀자고 괴롭혀서\" 의자에 묶고 흉기 살해","cpKorName":"SBS","summary":"<앵커> 끔찍한 사건 하나 더 보도해야 할 것 같습니다. 20대 여성이 40대 남자를 의자에 묶어 놓고 흉기로 찔러 살해했습니다. 숨진 남성이 오랫동안 쫓아다니며 사귀자고 괴롭혀 살해했다고 주장했습니다. KNN 정기형 기자가 보도합니다. <기자> 경남 김해시의 한 아파트입니다. 집 안이 어지럽고 곳곳이 핏자국입니다. 지난 15일 저녁 7시쯤 23살 A 여인","regDt":"20160118205009","importantYn":"Y","imageUrl":"http://t1.daumcdn.net/news/201601/18/sbsi/20160118205008330nmlo.jpg","ucccount":1312,"category":"society"},{"newsId":"20160118125215739","url":"http://v.media.daum.net/v/20160118125215739","title":"박 대통령, 민생구하기 입법촉구 서명","cpKorName":"연합뉴스","summary":"(서울=연합뉴스) 백승렬 기자 = 박근혜 대통령이 18일 경기도 성남시 판교테크노밸리 판교역 광장에서 민생구하기 입법촉구 천만서명운동본부가 추진하는 경제활성화법 처리를 촉구하는 서명을 하고 있다.    2016.1.18 srbaek@yna.co.kr (끝) [이 시각 많이 본 기사] <저작권자(c) 연합뉴스, 무단 전재-재배포 금지>","regDt":"20160118125215","importantYn":"N","imageUrl":"http://t1.daumcdn.net/news/201601/18/yonhap/20160118125214013mcet.jpg","ucccount":1288,"category":"politics"},{"newsId":"20160118095509560","url":"http://v.media.daum.net/v/20160118095509560","title":"안철수 \"'뭉치면 산다'로는 희망없어\"..총선연대 일축","cpKorName":"뉴스1","summary":"(서울=뉴스1) 박태정 기자,서미선 기자 = 안철수 국민의당 창당준비위원회 인재영입위원장은 18일 \"야권분열은 새누리당이 원하는 것이다\"는 문재인 더불어민주당 대표의 발언에 대해 \"지금은 야권분열이라면서 만년 야당의 기득권을 지키려 할 것이 아니라 수구지배체제에 강력 균열을 낼 때다\"며 야권연대 가능성을 일축했다. 안 위원장은 이날 서울 마포 당사에서 열","regDt":"20160118095509","importantYn":"Y","imageUrl":"http://t1.daumcdn.net/news/201601/17/NEWS1/20160117111051333woyl.jpg","ucccount":1271,"category":"politics"},{"newsId":"20160118142845252","url":"http://v.media.daum.net/v/20160118142845252","title":"朴대통령, 민생입법 1000만 서명운동 동참..국회 압박(종합2보)","cpKorName":"뉴스1","summary":"(서울=뉴스1) 윤태형 기자,유기림 기자,장은지 기자 = 박근혜 대통령이 18일 민생입법 촉구 1000만인 서명운동에 동참, 경제활성화법·노동개혁법·테러방지법 등 쟁점법안의 조속한 처리를 촉구하며 국회를 재차 압박했다. 박 대통령은 이날 오후 경기도 판교 네오트랜스 앞 광장에 설치된 ‘민생구하기 입법 촉구 천만 서명 운동’ 부스를 방문해 국회의 경제활성화","regDt":"20160118142845","importantYn":"Y","imageUrl":"http://t1.daumcdn.net/news/201601/18/NEWS1/20160118142600486nwvk.jpg","ucccount":1233,"category":"politics"},{"newsId":"20160118162708072","url":"http://v.media.daum.net/v/20160118162708072","title":"MB측 \"계좌추적 황당..검찰 명백히 설명해야\"","cpKorName":"연합뉴스","summary":"(서울=연합뉴스) 안용수 기자 = 이명박(MB) 전 대통령 측은 18일 지난 정부에서 장·차관, 청와대 수석비서관 등 고위직을 지낸 인사가 무더기로 검찰의 '계좌 조회'를 당한 데 대해 진상 규명을 요구했다. 이 전 대통령의 한 측근은 연합뉴스와의 통화에서 \"검찰이 지난 정부의 주요 인사들을 무더기로 계좌 추적했다는 언론보도는 황당하고 놀라운 일\"이라면서","regDt":"20160118162708","importantYn":"Y","imageUrl":"http://t1.daumcdn.net/news/201601/18/yonhap/20160118162707138hagl.jpg","ucccount":1193,"category":"politics"},{"newsId":"20160118050303995","url":"http://v.media.daum.net/v/20160118050303995","title":"[단독] 좌익효수급 '일베' 국정원 직원 3명 더 있다..檢 은폐의혹","cpKorName":"노컷뉴스","summary":"지난 2012년 대선 당시 극우성향의 인터넷 커뮤니티 사이트 '일간베스트'(일베)에 수천 개의 악성글을 올려 일명 '좌익효수'와 비슷한 시기에 검찰에 적발된 국정원 직원 3명의 존재가 확인됐다. 대선을 앞두고 야권 정치인과 전라도를 비하하는 등의 글을 유포해 모욕죄와 국정원법 위반 혐의로 기소된 '좌익효수'(대공수사팀 소속 유모씨)와 같은 국정원 직원들이","regDt":"20160118050303","importantYn":"Y","imageUrl":"","ucccount":1155,"category":"society"},{"newsId":"20160118160412075","url":"http://v.media.daum.net/v/20160118160412075","title":"朴대통령, 민생입법 1000만 서명운동 동참..국회 압박(종합3보)","cpKorName":"뉴스1","summary":"(서울=뉴스1) 윤태형 기자,유기림 기자,장은지 기자 = 박근혜 대통령이 18일 민생입법 촉구 1000만인 서명운동에 동참, 경제활성화법·노동개혁법·테러방지법 등 쟁점법안의 조속한 처리를 촉구하며 국회를 재차 압박했다. 박 대통령은 이날 오후 경기도 판교 네오트랜스 앞 광장에 설치된 ‘민생구하기 입법 촉구 천만 서명 운동’ 부스를 방문해 국회의 경제활성화","regDt":"20160118160412","importantYn":"Y","imageUrl":"http://t1.daumcdn.net/news/201601/18/NEWS1/20160118142600486nwvk.jpg","ucccount":990,"category":"politics"},{"newsId":"20160118210642034","url":"http://v.media.daum.net/v/20160118210642034","title":"'쯔위 사과' 미성년자 인권 문제로 확산..\"JYP 제소\"","cpKorName":"JTBC","summary":"[앵커] 이번 사태는 미성년자 인권 논란으로도 확산되고 있습니다. 정작 책임을 져야 할 어른들은 뒤에 빠지고, 어린 소녀를 앞세워 사과를 강요했다는 비판이 나오는 건데요. 한 민간단체는 국가인권위원회에 제소하겠다는 뜻도 밝혔습니다. 구동회 기자입니다. [기자] 1999년 대만에서 태어난 쯔위는 지난해 11월 방송 당시 열여섯 살이었습니다. 민감한 정치적","regDt":"20160118210642","importantYn":"Y","imageUrl":"http://t1.daumcdn.net/news/201601/18/JTBC/20160118210641249tmib.jpg","ucccount":952,"category":"foreign"},{"newsId":"20160118155804810","url":"http://v.media.daum.net/v/20160118155804810","title":"\"이승만을 어찌 國父라 하나\"..\"김종인은 전두환 국보위 참여\"","cpKorName":"매일경제","summary":"더불어민주당과 국민의당(안철수신당)이 본격적인 네거티브 난타전에 돌입했다. 더불어민주당이 ‘인재 영입’으로 탈당 후폭풍을 잠재우기 시작하자 탈당파가 반격에 나선 것이다. 문재인 더불어민주당 대표는 비주류의 탈당 명분을 없애기 위해 금명간 사퇴할 것으로 예상돼 양당 간 신경전이 극에 달하고 있다. 안철수 국민의당 인재영입위원장은 18일 확대기획조정회의에서","regDt":"20160118155804","importantYn":"Y","imageUrl":"","ucccount":952,"category":"politics"},{"newsId":"20160118165909203","url":"http://v.media.daum.net/v/20160118165909203","title":"아베 \"'위안부 강제연행 증거없다' 입장 불변\"(종합)","cpKorName":"연합뉴스","summary":"국회서 종전입장 재확인…\"한일위안부 합의, 전쟁범죄 인정 아니다\" 기시다 외무상 \"'성노예' 표현은 부적절\" (도쿄=연합뉴스) 최이락 조준형 특파원 = 아베 신조(安倍晋三) 일본 총리는 군위안부 강제연행의 증거가 없다는 입장을 재차 밝혔다. 아베 총리는 18일 도쿄 국회의사당에서 열린 참의원 예산위원회 회의에서 여당 의원의 질의에 답하면서 \"이제까지 정부","regDt":"20160118165909","importantYn":"Y","imageUrl":"http://t1.daumcdn.net/news/201601/18/yonhap/20160118165908288pvdu.jpg","ucccount":892,"category":"politics"},{"newsId":"20160118080806005","url":"http://v.media.daum.net/v/20160118080806005","title":"[포토엔]'대만 국기 논란' 트와이스 쯔위 '지친 17세 소녀'","cpKorName":"뉴스엔","summary":"[고양(경기)=뉴스엔 이한형 기자] MBC 설 특집 '2016 아이돌스타 육상·풋살·양궁 선수권대회'(이하 아육대) 개막식 녹화가 1월 18일 오전 경기 고양실내체육관에서 진행됐다. 이날 가수 트와이스가 '아육대'녹화장으로 이동하고 있다. 이번 설특집에도 인기 아이돌 스타들이 총출동한다. 수준급 축구 실력을 자랑하는 비스트 윤두준, 엑소 시우민부터 빅스","regDt":"20160118080806","importantYn":"Y","imageUrl":"http://t1.daumcdn.net/news/201601/18/newsen/20160118080805105sruh.jpg","ucccount":888,"category":"entertain"},{"newsId":"20160118050505003","url":"http://v.media.daum.net/v/20160118050505003","title":"[단독]\"쫓아다니지마\" 구애男 창틀에 묶고 살해한 20대女","cpKorName":"머니투데이","summary":"[머니투데이 이재윤 기자] 20대 여성이 자신을 쫓아 다니는 남성을 묶은 뒤 흉기로 찔러 살해한 사건이 발생해 경찰이 수사에 나섰다. 경남 김해중부경찰서는 헤어진 뒤에도 자신을 쫓아다니며 계속해서 구애한 남성을 흉기로 찔러 살해한 혐의 (살인)로 A씨(23·여)를 검거했다고 17일 밝혔다. 경찰에 따르면, A씨는 지난 15일 경남 김해시 자신의 집에","regDt":"20160118050505","importantYn":"Y","imageUrl":"http://t1.daumcdn.net/news/201601/18/moneytoday/20160118050504224ijdn.jpg","ucccount":861,"category":"society"},{"newsId":"20160118003200632","url":"http://v.media.daum.net/v/20160118003200632","title":"\"어린 쯔위 눈물, JYP 너무 한심해\" 대만 유학생 글","cpKorName":"국민일보","summary":"한 대만인 유학생이 한국에서 활동하는 대만인 출신 가수 쯔위를 둘러싼 논란에 대해 “쯔위 소속사인 JYP엔터테인먼트(JYP)의 대처에 화가 난다”는 취지의 글을 남겼다. 16일 국내 한 커뮤니티에는 자신을 서울대학교 대학원에 재학 중인 대만인 유학생이라고 이가 쓴 장문의 글이 올라왔다. 이 글을 올린 네티즌은 “글을 쓴 학생이 부탁해 대신해 올린다”고 밝","regDt":"20160118003200","importantYn":"N","imageUrl":"http://t1.daumcdn.net/news/201601/18/kukminilbo/20160118015059215gexe.jpg","ucccount":844,"category":"society"},{"newsId":"20160118030700513","url":"http://v.media.daum.net/v/20160118030700513","title":"문재인 19일 대표직 사퇴 선언할듯.. 사실상 '김종인 비대위'","cpKorName":"동아일보","summary":"[동아일보] 金 “선대위 빠를수록 文 사퇴 빨라질 것” 더불어민주당 문재인 대표(왼쪽)가 17일 국회 의원회관에서 열린 ‘더불어 컨퍼런스’ 행사에서 김종인 선거대책위원장과 악수하고 있다. 김 위원장은 이날 “선대위를 빨리 가동하면 할수록 (문 대표의) 사퇴 시점이 빨라질 것”이라고 말했다.전영한 기자 scoopjyh@donga.com 더불어민주당 문재인","regDt":"20160118030700","importantYn":"Y","imageUrl":"http://t1.daumcdn.net/news/201601/18/donga/20160118030659345kwkz.jpg","ucccount":812,"category":"politics"},{"newsId":"20160118101908943","url":"http://v.media.daum.net/v/20160118101908943","title":"'박영선, 천정배 모시자' 문자 보낸 문병호 의원","cpKorName":"뉴시스","summary":"【서울=뉴시스】고승민 기자 = 18일 오전 서울 마포구 국민의당 창당준비위원회에서 열린 확대기조회의에서 문병호 의원이 문자메세지를 보고 있다. 메세지에는 박영선, 천정배 의원 영입에 관한 내용이 적혀 있다. 2016.01.18. kkssmm99@newsis.com <저작권자ⓒ 공감언론 뉴시스통신사. 무단전재-재배포 금지.>","regDt":"20160118101908","importantYn":"Y","imageUrl":"http://t1.daumcdn.net/news/201601/18/newsis/20160118101907751nssg.jpg","ucccount":781,"category":"politics"},{"newsId":"20160118203006192","url":"http://v.media.daum.net/v/20160118203006192","title":"여당 '선진화법 개정' 돌입..단독 처리 '치밀한 작전'","cpKorName":"JTBC","summary":"[앵커] 새누리당은 국회선진화법을 바꾸기 위해 올인한 모습입니다. 4년 전 자신들이 주도해서 통과시켰던 법이지만 결정적일 때마다 발목이 잡혀 왔다고 주장해왔는데요. 오늘(18일) 이 개정안을 본회의에 올리기 위해 일종의 편법도 동원됐습니다. 첫 소식으로 보도해드립니다. 새누리당이 오늘 국회 운영위원회를 열어 선진화법을 무력화시키는 개정안을 상정했다가 곧바로","regDt":"20160118203006","importantYn":"Y","imageUrl":"http://t1.daumcdn.net/news/201601/18/JTBC/20160118203005167amzp.jpg","ucccount":737,"category":"politics"},{"newsId":"20160118183908975","url":"http://v.media.daum.net/v/20160118183908975","title":"경찰, '성매매 의심 6만명' 명단 입수..\"진위 파악중\"","cpKorName":"연합뉴스","summary":"(서울=연합뉴스) 설승은 기자 = 경찰이 6만여명의 성매매 고객 명단으로 불리는 엑셀 파일을 입수해 분석에 들어갔다. 서울지방경찰청 지능범죄수사대는 18일 해당 엑셀 파일을 입수해 분석 중이며, 일각의 주장처럼 성매매 조직이 관리한 고객 명단이 맞는지 진위를 파악할 계획이라고 밝혔다. 경찰은 이 파일을 입수한 경위는 밝히지 않았다. 앞서 여론기획 전문회사를","regDt":"20160118183908","importantYn":"Y","imageUrl":"http://t1.daumcdn.net/news/201509/24/yonhap/20150924074444667oucn.jpg","ucccount":715,"category":"society"},{"newsId":"20160118111104479","url":"http://v.media.daum.net/v/20160118111104479","title":"문재인 거취 표명 늦춰질 듯..19일 신년기자회견 \"결정된 바 없다\"","cpKorName":"머니투데이","summary":"[머니투데이 지영호 최경민  기자] [[the300]전병헌 \"문 대표 잘 매듭지을 수 있게 배려해줘야\"] 문재인 더불어민주당 대표의 거취와 관련한 입장표명이 다소 늦춰질 것으로 보인다. 그동안 19일로 예정된 당 선거대책위원회 인선과 함께 문 대표의 입장표명이 있을 것이란 관측이 많았다. 전병헌 최고위원은 18일 국회 당대표실에서 가진 최고위원회의 이","regDt":"20160118111104","importantYn":"Y","imageUrl":"http://t1.daumcdn.net/news/201601/18/moneytoday/20160118111103460ifyr.jpg","ucccount":713,"category":"politics"},{"newsId":"20160118195723501","url":"http://v.media.daum.net/v/20160118195723501","title":"'통일대박론' 지지도 하락..국민 41% \"북한=적\"","cpKorName":"연합뉴스","summary":"(서울=연합뉴스) 김호준 기자 = 박근혜 정부의 통일대박론에 대한 지지도가 전세대에 걸쳐 하락한 것으로 나타났다. 18일 통일부가 동아시아연구원 등에 용역 의뢰한 '통일 인식에 대한 세대 격차의 원인분석과 갈등 해소를 통한 국민통합 방안' 보고서에 따르면 통일대박론에 대한 20대의 지지도는 2014년 45.6%에서 지난해 32.4%로 13.2%포인트나 감소","regDt":"20160118195723","importantYn":"Y","imageUrl":"","ucccount":706,"category":"politics"},{"newsId":"20160118030630482","url":"http://v.media.daum.net/v/20160118030630482","title":"\"아빠 엄마가 오빠 버린것 같아요\" 동생 진술이 결정적 단서","cpKorName":"동아일보","summary":"[동아일보] 초등학생 아들의 시신을 훼손한 혐의를 받고 있는 최모 씨가 17일 오후 인천지법 부천지원에서 영장실질심사를 받은 뒤 나오고 있다. 부천=김미옥 기자 salt@donga.com 초등학생 아들의 시신을 훼손해 냉동 보관했던 아버지 최모 씨(34)가 17일 구속 수감됐다. 앞서 16일 아들이 숨지고 남편이 시신을 훼손한 사실을 알고도 경찰에 신고하","regDt":"20160118030630","importantYn":"Y","imageUrl":"http://t1.daumcdn.net/news/201601/18/donga/20160118030629648amvh.jpg","ucccount":653,"category":"society"},{"newsId":"20160118171253682","url":"http://v.media.daum.net/v/20160118171253682","title":"성남시 오늘부터 학교통해 무상교복 지원금 지급","cpKorName":"연합뉴스","summary":"(성남=연합뉴스) 이우성 기자 = 경기도 성남시는 '무상교복' 지원금 지급 첫 날인 18일 지역 16개 중학교가 각 학교 신입생 학부모에게 무상교복 지원금을 지급했다고 밝혔다. 성남지역 나머지 중학교도 20일까지 신입생 학부모에게 무상교복 지원금을 지급할 예정이다. 성남지역 중학교 49개교 중 이우중 1곳을 제외한 48개교가 학생들의 교복 착용을 의무화하","regDt":"20160118171253","importantYn":"Y","imageUrl":"","ucccount":647,"category":"society"},{"newsId":"20160118171905903","url":"http://v.media.daum.net/v/20160118171905903","title":"더민주 \"대통령이 서명운동? 지위·본분 망각\"","cpKorName":"노컷뉴스","summary":"더불어민주당은 18일 박근혜 대통령이 대한상공회의소의 '민생구하기 입법촉구 천만 서명운동'에 동참한데 대해 \"대통령으로서의 지위와 본분을 망각한 잘못된 판단으로 깊은 유감의 뜻을 밝힌다\"고 비판했다. 도종환 대변인은 \"행정부를 총괄하는 막강한 권한을 가진 대통령이 일반 국민들이 국가에 청원하기 위해 활용하는 서명운동을 하는 것은 어울리지 않는다\"며 이 같이","regDt":"20160118171905","importantYn":"Y","imageUrl":"http://t1.daumcdn.net/news/201601/18/nocut/20160118171903998oycw.jpg","ucccount":620,"category":"politics"},{"newsId":"20160118162543029","url":"http://v.media.daum.net/v/20160118162543029","title":"與 \"절차 하자 전혀 없다\"..선진화법 개정 강행","cpKorName":"뉴시스","summary":"【서울=뉴시스】손정빈 기자 = 새누리당 조원진 원내수석부대표는 18일 국회선진화법 개정 착수와 관련 \"절차에 전혀 하자가 없다. 국회법에 따라서 했다\"고 강조했다. 조 원내수석부대표는 이날 오후 국회에서 기자회견을 갖고 이같이 말했다. 새누리당은 앞서 국회 운영위원회 전체회의를 열어 권성동 의원이 대표 발의한 국회법 개정안을 회의에 상정했다. 야댱 위원들","regDt":"20160118162543","importantYn":"Y","imageUrl":"http://t1.daumcdn.net/news/201601/12/newsis/20160112102253002hpvg.jpg","ucccount":530,"category":"politics"},{"newsId":"20160118162403936","url":"http://v.media.daum.net/v/20160118162403936","title":"문재인, 19일 신년기자회견..사퇴 선언은 '아직'","cpKorName":"뉴시스","summary":"【서울=뉴시스】박주연 전혜정 기자 = 더불어민주당 문재인 대표가 오는 19일 신년 기자회견을 연다. 18일 더민주에 따르면, 문 대표는 19일 오전 10시 국회에서 기자회견을 열고 당내 현안과 더불어 쟁점 법안 등에 대한 자신의 입장을 밝힐 예정이다. 문 대표는 당초 지난 14일 기자회견을 갖고 박근혜 대통령의 대국민담화에 대해 반박할 예정이었지만 형식이","regDt":"20160118162403","importantYn":"Y","imageUrl":"http://t1.daumcdn.net/news/201601/18/newsis/20160118143026160sbld.jpg","ucccount":522,"category":"politics"},{"newsId":"20160118092755473","url":"http://v.media.daum.net/v/20160118092755473","title":"문재인 \"큰 변화 시작..사람·체질·문화 바뀔 것\"","cpKorName":"뉴시스","summary":"【서울=뉴시스】박주연 정윤아 기자 = 더불어민주당 문재인 대표는 18일 \"우리 당의 큰 변화가 시작됐다\"며 \"당의 껍데기만 달라진 것이 아니라 사람이 바뀌고, 체질이 바뀌고, 문화까지 바뀌는 것을 근본적인 목표로 하고 있다\"고 밝혔다. 문 대표는 이날 오전 국회에서 열린 당 최고위원회의에서 \"낡은 이념·지역주의 기득권 의존 정치가 아니라 국민의 삶을 바","regDt":"20160118092755","importantYn":"Y","imageUrl":"http://t1.daumcdn.net/news/201601/17/newsis/20160117122232311zovn.jpg","ucccount":500,"category":"politics"},{"newsId":"20160118103506718","url":"http://v.media.daum.net/v/20160118103506718","title":"국민의당 현역 의원 13명 모여 회의..교섭단체 구성 눈앞?","cpKorName":"머니투데이","summary":"[머니투데이 김태은  기자] [[the300]더민주 탈당 추세 주춤…박영선 합류 불투명] 국민의당에 합류한 현역 국회의원 13명이 한 자리에 모였다. 이제까지 세 확장 추세를 고려하면 교섭단체 구성이 초읽기에 들어갔다는 관측이 나온다. 정치권에선 박영선 더불어민주당 전 원내대표의 탈당 여부가 관건이 될 것으로 보고있다. 국민의당은 18일 서울 마포구 국","regDt":"20160118103506","importantYn":"Y","imageUrl":"http://t1.daumcdn.net/news/201601/18/moneytoday/20160118103505761btlq.jpg","ucccount":498,"category":"politics"},{"newsId":"20160118030710526","url":"http://v.media.daum.net/v/20160118030710526","title":"\"보육-사교육비 감당 못해\".. '무자식 상팔자' 택한 젊은층","cpKorName":"동아일보","summary":"[동아일보] “우리, 아무래도 아이를 갖는 건 좀 그렇겠지?” 경기 성남시의 한 중소기업에 다니는 M 씨(43)는 9년 전 남편을 만나 ‘골드미스’ 생활을 청산했다. M 씨는 평소 아이와 동물을 좋아하는 스타일. 하지만 신혼 초 ‘무자녀 인생’을 결정하는 데에는 오랜 시간이 걸리지 않았다. 임신을 하기에는 다소 늦은 나이여서 건강한 아이를 낳을 수 있을지","regDt":"20160118030710","importantYn":"Y","imageUrl":"http://t1.daumcdn.net/news/201601/18/donga/20160118030708694fnix.jpg","ucccount":494,"category":"society"},{"newsId":"20160118104605195","url":"http://v.media.daum.net/v/20160118104605195","title":"\"너 되게 낯설다\"..더민주의 '인재자랑대회'","cpKorName":"한겨레","summary":"[한겨레] 정치BAR_“김종인, 김종인”연호…여긴 어디? 1월17일, 평소같으면 조용했을 일요일 오전 국회 의원회관 대회의실 주변은 사람들로 북적였습니다. 더불어민주당(더민주)이 세계적인 지식 강연 프로그램인 테드(TED)를 본따 개최한 ‘더불어 컨퍼런스 사람의 힘’행사가 열렸기 때문입니다. 총선을 앞두고 더민주가 영입한 표창원 전 경찰대 교수·김병관 웹젠","regDt":"20160118104605","importantYn":"Y","imageUrl":"http://t1.daumcdn.net/news/201601/18/hani/20160118104603690onbr.jpg","ucccount":494,"category":"politics"},{"newsId":"20160118052010038","url":"http://v.media.daum.net/v/20160118052010038","title":"文-安 러브콜 받는 박영선, 뭘 고민하길래 뜸 들이나","cpKorName":"뉴스1","summary":"(서울=뉴스1) 조소영 기자 = 박영선 더불어민주당 전 원내대표가 향후 거취를 놓고 고민을 거듭하는 모습이다. 자당 문재인 대표와 국민의당 창당을 준비 중인 안철수 의원이 번갈아가며 '러브콜'을 보내고 있지만, 박 전 원내대표는 어느 한쪽으로도 쉽사리 마음을 내어주지 않는 모양새다. 박 전 원내대표는 대표적인 여성 정치인으로 대중적인 인지도가 있는데다 지역","regDt":"20160118052010","importantYn":"Y","imageUrl":"http://t1.daumcdn.net/news/201601/18/NEWS1/20160118052009120xmil.jpg","ucccount":492,"category":"politics"},{"newsId":"20160118120217566","url":"http://v.media.daum.net/v/20160118120217566","title":"김종인 효과? 탈당 주춤..박영선·정운찬 거취가 최종고비","cpKorName":"연합뉴스","summary":"박영선 잔류 쪽 무게 관측…\"이번주내 결정\" 주변인사들 전해 (서울=연합뉴스) 송수경 류지복 서혜림 기자 = 분당 사태를 맞아 휘청이던 더불어민주당이 '김종인 효과'를 보고 있다. 문재인 대표의 삼고초려로 김 위원장이 14일 전격 영입돼 문 대표의 조기사퇴를 기정사실화하며 '원톱 리더십' 구축에 나선 이후 일부 여론조사에서 호남 지지율이 안철수 신당을 앞","regDt":"20160118120217","importantYn":"Y","imageUrl":"http://t1.daumcdn.net/news/201601/18/yonhap/20160118120216071piwr.jpg","ucccount":484,"category":"politics"},{"newsId":"20160118170943566","url":"http://v.media.daum.net/v/20160118170943566","title":"경찰청장 \"대사관 앞 집회 '금지', 법원 가보자\"","cpKorName":"머니투데이","summary":"[머니투데이 김민중 기자] \"법원으로 한 번 가보자. 경찰은 사법부의 감시와 비판을 수용할 것이다\"(강신명 경찰청장) 경찰이 대사관 앞 집회를 '허가제'로 운영한다는 일각의 비판을 정면으로 반박했다. 강신명 경찰청장은 18일 서울 미근동 경찰청에서 기자간담회에서 '소녀상 지킴이' 대학생들의 옛 일본대사관 앞 '미신고집회'와 관련, '현행법은 대사관","regDt":"20160118170943","importantYn":"Y","imageUrl":"http://t1.daumcdn.net/news/201601/18/moneytoday/20160118170942456wqjs.jpg","ucccount":472,"category":"society"},{"newsId":"20160118131800352","url":"http://v.media.daum.net/v/20160118131800352","title":"[친절한 쿡기자] 태극기 훼손 대만女 영상까지.. 쯔위 사태로 갈등 폭발","cpKorName":"국민일보","summary":"걸그룹 트와이스 멤버 쯔위(17)의 국적 논란으로 한국과 대만 사이에서 감정의 골이 깊어지고 있습니다. 태극기를 훼손한 대만 여성들의 영상이 쯔위 사태에 대한 항의 차원으로 잘못 알려지면서 우리나라 SNS가 요동치는 해프닝까지 벌어졌습니다. 트위터 타임라인은 18일 ‘태극기를 훼손하는 대만 여자의 수준’이라는 제목의 유튜브 영상을 놓고 들썩거렸습니다. 대만","regDt":"20160118131800","importantYn":"N","imageUrl":"http://t1.daumcdn.net/news/201601/18/kukminilbo/20160118151300782xdxc.jpg","ucccount":470,"category":"culture"},{"newsId":"20160118141318379","url":"http://v.media.daum.net/v/20160118141318379","title":"[포토엔]서인영, 위 아래 눈 둘곳 없는 파격 의상","cpKorName":"뉴스엔","summary":"[뉴스엔 안성후 기자] MBC 새 수목드라마 '한번 더 해피엔딩' 제작발표회가 1월 18일 오후 2시 서울 마포구 상암 MBC 골든마우스홀에서 열렸다. 이날 권성창 PD를 비롯해 배우 장나라, 정경호, 권율, 유인나, 유다인, 서인영 등이 참석해 자리를 빛냈다. ‘한번 더 해피엔딩’은 서른이 훌쩍 넘어버린 1세대 요정 걸그룹의 그 후 그리고 그들과 엮이는","regDt":"20160118141318","importantYn":"Y","imageUrl":"http://t1.daumcdn.net/news/201601/18/newsen/20160118141317900yfdy.jpg","ucccount":460,"category":"entertain"},{"newsId":"20160118084750072","url":"http://v.media.daum.net/v/20160118084750072","title":"文, 인재 영입 12·13호에 '박원순 사람' 김민영·오성규","cpKorName":"뉴스1","summary":"(서울=뉴스1) 박응진 기자 = 김민영 전 참여연대 사무처장.© News1문재인 더불어민주당 대표는 18일 20대 총선 관련 인재 12·13호로 각각 김민영(49) 전 참여연대 사무처장과 오성규(49) 전 서울시 시설관리공단 이사장을 영입한다. 박원순 서울시장과 함께 서울시정에 참여했던 두 사람은 이날 오전 국회에서 입당 기자회견을 갖는다. 더민주는 두","regDt":"20160118084750","importantYn":"Y","imageUrl":"http://t1.daumcdn.net/news/201601/18/NEWS1/20160118084749457lfbv.jpg","ucccount":455,"category":"politics"},{"newsId":"20160118030708523","url":"http://v.media.daum.net/v/20160118030708523","title":"검찰, 이명박 정부 고위직 무더기 계좌 조회.. 장관·수석 등 최소 10여명","cpKorName":"조선일보","summary":"이명박 정부에서 장관이나 청와대 수석비서관을 지낸 인사들 최소 10여명이 작년 6월을 전후해 검찰로부터 계좌 조회를 당한 것으로 17일 전해졌다. 지난 정부에서 장관을 지낸 A씨는 본지 통화에서 \"작년 12월 은행으로부터 '서울중앙지검의 요청으로 금융정보를 제공했다'는 통보를 받았다\"며 \"최근 다른 인사들 10여명도 계좌 조회를 당한 사실을 알게 됐다\"고","regDt":"20160118030708","importantYn":"Y","imageUrl":"","ucccount":454,"category":"politics"},{"newsId":"20160118152931379","url":"http://v.media.daum.net/v/20160118152931379","title":"아기 던져 살해한 발달장애아 막지 못한 활동보조인 무죄","cpKorName":"연합뉴스","summary":"법원 \"활동보조인 업무에 교육·훈계는 포함 안돼\" (부산=연합뉴스) 오수희 기자 = 2014년 12월 3일 오후 4시 6분께 부산 사하구에 있는 한 사회복지관 3층 복도. 발달장애 1급 장애인 이모(20)군은 혼자 놀고 있던 A(2)군을 발견하고 3층 옥외 비상계단으로 데려가 A군을 안아 들고 1층 바닥으로 던졌다. 이군이 A군을 비상계단으로 데리고 가는","regDt":"20160118152931","importantYn":"Y","imageUrl":"http://t1.daumcdn.net/news/201510/06/yonhap/20151006152158752yzdq.jpg","ucccount":454,"category":"society"},{"newsId":"20160118151855760","url":"http://v.media.daum.net/v/20160118151855760","title":"시신훼손 초등생 아버지 \"나도 어릴적 체벌 많이받아\"","cpKorName":"연합뉴스","summary":"범죄심리 분석서 이기적 성향, 미숙한 자녀양육 형태 등 확인 경찰 '부작위에 의한 살인 혐의' 적용 검토 (부천=연합뉴스) 신민재 최은지 기자 = 초등학생 아들의 시신을 잔인하게 훼손해 냉동 보관한 아버지(34)는 경찰 조사에서 자신도 어렸을 때부터 친어머니로부터 체벌을 많이 받았다고 진술한 것으로 나타났다. 경찰은 아들의 시신을 훼손해 수년간 집 냉장고에","regDt":"20160118151855","importantYn":"Y","imageUrl":"http://t1.daumcdn.net/news/201601/18/yonhap/20160118151854146pwly.jpg","ucccount":448,"category":"society"},{"newsId":"20160118140657065","url":"http://v.media.daum.net/v/20160118140657065","title":"JYP 측 \"쯔위 입장 발표 강요? 억측이다..부모님 상의\"","cpKorName":"TV리포트","summary":"[TV리포트=김예나 기자] JYP엔터테인먼트 측이 트와이스 멤버 쯔위의 입장 발표에 대해 강요로 진행된 것이 아니라고 주장했다. 18일 오후 JYP엔터테인먼트 측은 “트와이스 멤버 쯔위의 입장 발표에 대한 일부 오해에 대해 JYP 엔터테인먼트의 입장을 밝힙니다”며 “이번 쯔위의 입장 발표는 쯔위가 미성년자이므로 처음부터 부모님과 함께 상의했고 회사는 부모님","regDt":"20160118140657","importantYn":"Y","imageUrl":"http://t1.daumcdn.net/news/201601/18/tvreport/20160118140657233ntwb.jpg","ucccount":423,"category":"entertain"},{"newsId":"20160118210509984","url":"http://v.media.daum.net/v/20160118210509984","title":"지원금 끊긴 유치원..\"대출 받아 교사 월급\"","cpKorName":"SBS","summary":"<앵커> 누리과정 예산문제가 해결의 실마리를 찾지 못하면서 서울과 경기 사립유치원들은 당장 며칠 뒤에 지급해야 하는 교사 월급이 걱정입니다. 교육부 장관과 시·도교육감이 만났지만, 별 소득 없이 헤어졌습니다. 김정기 기자입니다. <기자> 서울에 있는 이 사립 유치원의 교사는 25명입니다. 오는 25일 교사 월급으로 모두 6천여만 원이 지급돼야 합니다. 예년","regDt":"20160118210509","importantYn":"Y","imageUrl":"http://t1.daumcdn.net/news/201601/18/sbsi/20160118210507848zqhc.jpg","ucccount":413,"category":"society"},{"newsId":"20160118141105266","url":"http://v.media.daum.net/v/20160118141105266","title":"올해 청년 5만명 인턴제 실시..1인당 최대 570만원 지원","cpKorName":"헤럴드경제","summary":"[헤럴드경제=원승일 기자] 정부는 올해 총 5만명 규모의 ‘청년취업인턴제’를 실시한다. 인턴을 정규직으로 채용한 기업에는 1인당 최대 570만원의 지원금을 준다. 고용노동부는 청년들이 선호하는 강소ㆍ중견기업의 인턴채용 규모를 지난해 1만5000명에서 올해 3만명으로 늘리고, 중소기업 2만명까지 모두 5만명을 대상으로 지원할 계획이라고 18일 밝혔다. 고용","regDt":"20160118141105","importantYn":"Y","imageUrl":"http://t1.daumcdn.net/news/201601/18/ned/20160118141105527ufnk.jpg","ucccount":408,"category":"society"},{"newsId":"20160118060115398","url":"http://v.media.daum.net/v/20160118060115398","title":"[단독]여관 '장기투숙' 60대男 목매 숨져..주인에 \"신세 많았다\"","cpKorName":"머니투데이","summary":"[머니투데이 윤준호 기자, 구유나 기자] [현장서 유서 발견 \"날 춥지 않았다면 물에 빠졌을텐데, 목맨 모습 보여 죄송\"…경찰 \"생활고 가능성 중점 수사\"] 여관에서 혼자 살아온 60대 남성이 숨진 채 발견됐다. 18일 서울 서부경찰서와 소방당국 등에 따르면 전날 낮 12시30분쯤 서울 은평구 한 여관에서 안모씨(67)가 목을 매 숨진 채로 발견됐다.","regDt":"20160118060115","importantYn":"Y","imageUrl":"http://t1.daumcdn.net/news/201601/18/moneytoday/20160118060114463lace.jpg","ucccount":402,"category":"society"},{"newsId":"20160118190145467","url":"http://v.media.daum.net/v/20160118190145467","title":"[포토] 한파주의보 속에서도 소녀상 지키는 대학생들","cpKorName":"한국일보","summary":"한파주의보 속에서 추위 견디는 대학생들 추위에 옷을 입은 평화의 소녀상 대학생 지킴이들이 이불을 덮고 추위를 견디고 있다. 18일 오후 '평화의 소녀상'을 지키는 대학생들이 한파주의보에 불구하고 서울 종로구 주한일본대사관 앞에서 19일째 노숙농성을 이어갔다. 이들 대학생들은 일본군 위안부 한일협상 폐기 대학생 대책위 소속으로 지난해 연말부터 '평화의 소녀상","regDt":"20160118190145","importantYn":"Y","imageUrl":"http://t1.daumcdn.net/news/201601/18/hankooki/20160118190144348gdhx.jpg","ucccount":387,"category":"society"},{"newsId":"20160118182923700","url":"http://v.media.daum.net/v/20160118182923700","title":"'일베' 들락날락 댓글 단 국정원 직원 3명 더 있었다","cpKorName":"연합뉴스","summary":"은폐 의혹 제기…檢 \"2013년 참고인 조사 후 혐의없어 불입건\" (서울=연합뉴스) 전성훈 기자 = 2012년 대선을 전후해 '좌익효수'라는 필명을 쓴 국가정보원 직원 외에 다른 직원 3명이 인터넷 공간에서 정치적 성향의 글을 올리다가 검찰에서 조사를 받은 사실이 뒤늦게 확인됐다. 18일 검찰에 따르면 국정원 대선 개입 의혹 사건을 수사한 서울중앙지검 특","regDt":"20160118182923","importantYn":"Y","imageUrl":"http://t1.daumcdn.net/news/201511/10/yonhap/20151110120907567wygf.jpg","ucccount":383,"category":"society"},{"newsId":"20160118210001874","url":"http://v.media.daum.net/v/20160118210001874","title":"강남구청장, 서울시장 면담요청..'앙숙 관계' 해소할까(종합)","cpKorName":"연합뉴스","summary":"신연희 구청장 \"새해에는 원활한 관계 유지\"…市 \"면담 검토 중\" (서울=연합뉴스) 이정현 기자 = 한전부지 개발에 따른 공공기여금 사용처 등을 놓고 서울시와 갈등을 빚어온 신연희 강남구청장이 박원순 서울시장에게 면담을 요청해 성사될지 주목된다. 18일 양측에 따르면 신 구청장은 이달 15일 서울시에 박 시장과의 면담 요청 공문을 발송했다. 신 구청장은 서","regDt":"20160118210001","importantYn":"Y","imageUrl":"http://t1.daumcdn.net/news/201601/18/yonhap/20160118210009189ggxi.jpg","ucccount":382,"category":"society"},{"newsId":"20160118201555883","url":"http://v.media.daum.net/v/20160118201555883","title":"문재인 이번 주 사퇴 '무게'..내일 회견 주목","cpKorName":"MBN","summary":"【 앵커멘트 】더불어민주당 문재인 대표가 내일 신년 기자회견을 앞두고 마음의 부담이 강한 모양입니다.오늘 하루 동안에만 내일 회견을 연기했다가 다시 하기로 하는 등 오락가락했다고 전해집니다.그건 바로 내일 그 기자회견에서 자신이 물러날지, 말지에 관한 거취를 밝혀야 하기 때문인데요.내일 문 대표, 과연 사퇴 의사를 밝힐까요.박준우 기자가 보도합니다. 【 기","regDt":"20160118201555","importantYn":"Y","imageUrl":"http://t1.daumcdn.net/news/201601/18/mbn/20160118201554163cfvb.jpg","ucccount":381,"category":"politics"},{"newsId":"20160118172100991","url":"http://v.media.daum.net/v/20160118172100991","title":"\"쯔위 사태, 중국에 납작 엎드린 JYP\" 현재 대만 분위기 짤","cpKorName":"국민일보","summary":"대만 독립 지지 논란에 휩싸인 걸그룹 트와이스 멤버 쯔위(17)의 공개 사과가 대만 국민들의 화를 돋웠다. “중국은 하나”라는 말이 사태를 키운 모양새다. ‘현재 대만 분위기’라는 제목의 한 컷 사진이 18일 국내 여러 커뮤니티에 올랐다. 쯔위의 사과 영상 촬영 상황을 가정해 그린 그림으로 보인다. 이는 실제 대만 SNS에 퍼지고 있는 이미지다. 사진 속","regDt":"20160118172100","importantYn":"Y","imageUrl":"http://t1.daumcdn.net/news/201601/18/kukminilbo/20160118172059141tnaw.jpg","ucccount":378,"category":"culture"},{"newsId":"20160118142735190","url":"http://v.media.daum.net/v/20160118142735190","title":"쯔위와 박진영은 뭘 잘못했을까?[이슈와치]","cpKorName":"뉴스엔","summary":"쯔위와 박진영은 뭘 잘못했을까?[이슈와치] 트와이스 쯔위에 대한 중국의 비난이 수그러드는 가운데 사태를 수습하려던 JYP 수장 박진영은 엉뚱하게 한국에서 야비한 사업가 겸 비겁한 선배가 됐고, 쯔위에 대한 동정의 여론이 확산되고 있다. 과연 쯔위와 박진영, 이들은 그렇게 국제적으로 민감한 정치적 색깔을 둘러싼 공방의 희생양이 될 만큼 범국가적 잘못을 저질","regDt":"20160118142735","importantYn":"Y","imageUrl":"http://t1.daumcdn.net/news/201601/18/newsen/20160118142733533eadm.jpg","ucccount":370,"category":"entertain"},{"newsId":"20160118153959950","url":"http://v.media.daum.net/v/20160118153959950","title":"[종합]더민주, '선진화법' 개정작업 반발..의장·여야 회동 불참","cpKorName":"뉴시스","summary":"'여야 회동'은 야당 불참한 가운데 반쪽으로 진행 【서울=뉴시스】박주연 김태규 손정빈 기자 = 더불어민주당이 새누리당의 국회선진화법 개정 작업에 반발, 18일 오후 3시로 예정됐던 국회의장과 여야 원내대표-정책위의장간의 회동에 불참했다. 더민주는 새누리당이 이날 운영위를 단독 소집해 국회의장의 직권상정(심사기간 지정) 요건을 확대하는 국회법 개정 절차","regDt":"20160118153959","importantYn":"Y","imageUrl":"http://t1.daumcdn.net/news/201601/18/newsis/20160118141945767uldu.jpg","ucccount":369,"category":"politics"},{"newsId":"20160118191759788","url":"http://v.media.daum.net/v/20160118191759788","title":"누카가 의원 \"韓정부, 정대협과 소녀상 이전 논의중\"","cpKorName":"뉴스1","summary":"(서울=뉴스1) 장용석 기자 = 누카가 후쿠시로(額賀福志郎) 일본 자민당 중의원 의원은 18일 주한일본대사관 앞의 일본군 위안부 소녀상과 관련 \"현재 한국 정부와 소녀상을 설치한 정대협(한국정신대문제대책협의회)간 이전 논의 상황을 끝까지 지켜보겠다\"고 말했다. NHK에 따르면, 한일의원연맹 일본 측 회장인 누카가 의원은 이날 나고야(名古屋)에서 한 강연을","regDt":"20160118191759","importantYn":"Y","imageUrl":"http://t1.daumcdn.net/news/201601/18/NEWS1/20160118191759007gzky.jpg","ucccount":344,"category":"politics"},{"newsId":"20160118210009881","url":"http://v.media.daum.net/v/20160118210009881","title":"변호사 2만명 시대, 사법연수원 수료생 절반이 '백수'","cpKorName":"MBC","summary":"[뉴스데스크]◀ 앵커 ▶ 오늘 사법연수원의 수료식이 있었습니다. 모두가 부러워하는 사시 합격생들. 하지만, 어렵게 공부해서 사회 첫발 내딛는 수료식 분위기가 마냥 즐겁지는 않았다는데요. 전기영 기자가 다녀왔습니다. ◀ 리포트 ▶ 사법시험을 통과하고 2년간의 실무 연수까지 마친 사법연수원생들. 수료식에 참석했지만 표정이 밝지만은 않습니다. 올해 수료생 356","regDt":"20160118210009","importantYn":"Y","imageUrl":"http://t1.daumcdn.net/news/201601/18/imbc/20160118210007491bhec.jpg","ucccount":343,"category":"society"},{"newsId":"20160118170509427","url":"http://v.media.daum.net/v/20160118170509427","title":"세일에 또 세일.. 아웃도어 업계의 고민","cpKorName":"서울경제","summary":"#. 17일 오후 금천구 가산동의 한 대형 아웃렛에 입점한 블랙야크 매장에 ‘30~50% 세일’ 깃발이 걸려있다. 하지만 큰 폭의 할인에도 손님들에게 별로 환영받지 못하는 모습이다. 매장 앞쪽에 설치한 초특가 상품 매대 때문. 2015년 7월 생산 다운제품들을 무려 60% 이상 할인, 판매중이었다. 이월상품이라기에는 너무 ‘어린 나이’. 그런데도 매장에","regDt":"20160118170509","importantYn":"Y","imageUrl":"","ucccount":342,"category":"economic"},{"newsId":"20160118133249796","url":"http://v.media.daum.net/v/20160118133249796","title":"'응팔', 뒤끝 개운치 않아도 기꺼이 칭찬하는 이유","cpKorName":"엔터미디어","summary":"‘응팔’, 이 정도로 행복감을 전해준 드라마 있었던가 [엔터미디어=김교석의 어쩌다 네가] 사실, 덕선(혜리)의 남편이 누구인지는 tvN 금토드라마 <응답하라 1988>에서 중요치 않았다. 주인공인 덕선과 택이(박보검)의 결혼식 대신 보라(류혜영)와 선우(고경표)의 결혼식이 마지막 화를 장식한 이유이기도 하다. <응팔>은 청춘을 말하지만 연애대신 잊혀진, 잊","regDt":"20160118133249","importantYn":"Y","imageUrl":"http://t1.daumcdn.net/news/201601/18/entermedia/20160118133247904pxei.jpg","ucccount":333,"category":"entertain"},{"newsId":"20160118110904337","url":"http://v.media.daum.net/v/20160118110904337","title":"세계 최강 '빚 권하는 사회' 한국","cpKorName":"헤럴드경제","summary":"전화 한통이면 500만원 대출집 담보땐 집값70%까지 빌려줘신용카드 할부제도 빚 부추겨가계부채 1200조 육박 눈덩이 ‘세계적으로 가장 관대한 신용카드 할부제도, 전화 한통이면 500만원까지 단박 대출, 집값의 70%까지 빚을 내주는 주택담보대출비율(LTV)…. 우리 나라는 전세계적으로 유례를 찾기 힘들 정도로 빚을 내기 쉬운 경제구조를 지녔다. 빚을 부추","regDt":"20160118110904","importantYn":"Y","imageUrl":"http://t1.daumcdn.net/news/201601/18/ned/20160118110904156uzlq.jpg","ucccount":328,"category":"economic"},{"newsId":"20160118233453295","url":"http://v.media.daum.net/v/20160118233453295","title":"安신당 \"기득권포기..현역도 경선참여\"..첫 의총은 연기(종합2보)","cpKorName":"연합뉴스","summary":"의원들 \"전략공천도 맞지 않다\"…'물갈이 여론'도 견제 선거구 획정안 \"지역구 253+비례 47석안 조속 합의해야\" 문병호, 安에 \"박영선에게 당대표·서울시장 공천 제안해야\" (서울=연합뉴스) 조성흠 박수윤 기자 = '국민의당'(가칭) 현역 의원 전원이 총선 후보 공천을 위한 당내 경선에 참여하기로 결정한 것으로 18일 알려졌다. 의원들은 오는 19일 첫","regDt":"20160118233453","importantYn":"Y","imageUrl":"","ucccount":322,"category":"politics"},{"newsId":"20160118013047972","url":"http://v.media.daum.net/v/20160118013047972","title":"김종인 \"최고위 해체\".. 文, 내일 사퇴 가능성","cpKorName":"서울신문","summary":"[서울신문]더불어민주당 김종인 선거대책위원장이 선대위 구성과 함께 현 최고위원회의는 해체한다고 17일 밝혔다. 김 위원장은 문재인 대표가 19일로 알려진 신년 기자회견에서 거취를 표명할 것으로 예상했다. 김 위원장은 이날 저녁 서울신문 기자와 만난 자리에서 “최고위는 없어진다”면서 이같이 밝혔다. 이어 “문 대표는 본인이 가급적 빨리 (사퇴)하겠다고 했다”","regDt":"20160118013047","importantYn":"Y","imageUrl":"http://t1.daumcdn.net/news/201601/18/seoul/20160118013045520fkrd.jpg","ucccount":317,"category":"politics"},{"newsId":"20160118183004722","url":"http://v.media.daum.net/v/20160118183004722","title":"\"황안은 양안 교류의 천고의 죄인\"..쯔위 동정 여론 확산","cpKorName":"중앙일보","summary":"한국 걸그룹 트와이스(TWICE)의 대만 멤버 쯔위(중국명 저우쯔위·周子瑜·16) 사태가 전환점을 맞는 조짐을 보이고 있다. 중국과 대만에서 쯔위에 대한 비난이 수그러들며 동정 여론이 힘을 얻고 있다. 쯔위는 지난해 11월 공개된 MBC 예능프로그램 ‘마이 리틀 텔레비전’ 사전 인터넷 방송에서 대만 국기를 흔든 사실이 뒤늦게 알려지며 지난 16일 대만 총통","regDt":"20160118183004","importantYn":"Y","imageUrl":"http://t1.daumcdn.net/news/201601/18/joongang/20160118183002883rvmt.jpg","ucccount":316,"category":"foreign"},{"newsId":"20160118171603812","url":"http://v.media.daum.net/v/20160118171603812","title":"\"오죽하면 국민 나섰겠나\"..朴대통령 '서명행동'으로 여론결집","cpKorName":"연합뉴스","summary":"서명운동 참여 이례적…국회 교착 계속되자 '국민과 함께 행동' 여야 합의도 없고, 직권상정도 안할 경우 靑 돌파수단 없어 (서울=연합뉴스) 강병철 기자 = 박근혜 대통령이 18일 대한상공회의소 등 경제단체가 진행하는 '민생구하기 입법촉구 1천만인 서명운동'에 직접 참여했다. 국가원수이자 행정부 수반인 대통령이 경제단체 등 민간에서 진행하는 서명운동에 '국민","regDt":"20160118171603","importantYn":"Y","imageUrl":"http://t1.daumcdn.net/news/201601/18/yonhap/20160118171602351rtvz.jpg","ucccount":308,"category":"politics"},{"newsId":"20160118013522995","url":"http://v.media.daum.net/v/20160118013522995","title":"[생각나눔] 택시기사 25%가 '할아버지'..  \"안전 위협\" vs \"직업선택 자유\"","cpKorName":"서울신문","summary":"[서울신문] “백발의 택시운전자를 규제해야 한다”, “누구나 직업 선택의 자유가 있다. 노인들의 택시 운전을 규제해서는 안 된다”. 우리 사회가 급속하게 노령화되면서 노인 자가운전자뿐 아니라 노인 택시운전자에 대한 논란이 뜨거운 감자로 떠올랐다. 지난해 4월 80대가 운전하는 택시가 신라호텔로 돌진한 사고는 재벌 2세가 사고 책임을 묻지 않아 사회적 화제가","regDt":"20160118013522","importantYn":"Y","imageUrl":"http://t1.daumcdn.net/news/201601/18/seoul/20160118013520671tfup.jpg","ucccount":302,"category":"society"},{"newsId":"20160118092819503","url":"http://v.media.daum.net/v/20160118092819503","title":"임경신, '쯔위 사태' 조롱 \"사과 대본외울 시간 없었다\"","cpKorName":"엑스포츠뉴스","summary":"[엑스포츠뉴스=전아람 기자] 중국배우 임경신(린겅신)이 쯔위 사과에 대한 부정적인 반응을 드러냈다.   임경신은 지난 16일 자신의 웨이보를 통해 JYP엔터테인먼트 공식 웨이보에 게재된 쯔위의 사과 동영상을 리포스트 하며 자신의 생각을 덧붙였다.   임경신은 글을 통해 \"사과가 너무 갑작스러워서 대본을 외울 시간도 없었다\"고 말하며 웃는 모습의 이모티콘을","regDt":"20160118092819","importantYn":"Y","imageUrl":"http://t1.daumcdn.net/news/201601/18/xportsnews/20160118092818891mjtn.jpg","ucccount":294,"category":"entertain"},{"newsId":"20160118202539129","url":"http://v.media.daum.net/v/20160118202539129","title":"갑자기 멈춰버린 더민주 호남의원 탈당 러시. 왜","cpKorName":"한국일보","summary":"더불어민주당(더민주)의 호남 탈당 러시가 주춤거리고 있다. 전북 지역 국회의원 9명이 당 잔류를 공식 선언했고, 탈당이 예상됐던 광주ㆍ전남의 ‘후발대 탈당파’의원들도 당 잔류 혹은 상황 관망으로 돌아섰다. 당 안팎에서는 김종인 선거대책위원장 영입 이후 더민주에 부정적이었던 호남 민심이 돌아서는 분위기에다 탈당 후 행선지로 유력했던 안철수 의원의 국민의당에서","regDt":"20160118202539","importantYn":"Y","imageUrl":"","ucccount":275,"category":"politics"},{"newsId":"20160118164403660","url":"http://v.media.daum.net/v/20160118164403660","title":"\"한노총 달래려고 줄 건 다 줬는데\"..노동개혁 방향 잃나","cpKorName":"매일경제","summary":"노동개혁을 둘러싼 노·정 갈등이 확대되는 상황에서 ‘내어 줄 것은 다 내어준’ 경영계의 불만도 커지고 있다. 9·15 노사정대타협에서 노사정 가운데 가장 불이익을 받았다는 게 경영계 안팎의 인식이다. 하지만 이 마저도 한국노총을 설득하는 과정에서 방향전환이 반복되고 있다. 이에 경영계 안팎에서는 노동개혁의 본질이 흔들리고 있다는 지적도 나오고 있다. 한국경","regDt":"20160118164403","importantYn":"Y","imageUrl":"","ucccount":264,"category":"politics"},{"newsId":"20160118101303655","url":"http://v.media.daum.net/v/20160118101303655","title":"安 \"文 같은 인식과 태도 때문에 정권 내준 것\"","cpKorName":"노컷뉴스","summary":"더불어민주당 문재인 대표가 \"집권세력이 바라는 것이 야권의 분열\"이라며 '국민의당'(가칭)을 비판한데 대해 안철수 인재영입위원장이 18일 \"그런 인식과 태도 때문에 정권을 내주고 무기력하게 끌려 다니는 상황을 만든 것\"이라며 역공에 나섰다. 안 위원장은 이날 오전 서울 마포구 국민의당 당사에서 열린 확대기획조정회의에서 \"지금은 야권분열이라면서 만년 야당의","regDt":"20160118101303","importantYn":"Y","imageUrl":"http://t1.daumcdn.net/news/201601/18/nocut/20160118101302715ttqb.jpg","ucccount":261,"category":"politics"},{"newsId":"20160118115304017","url":"http://v.media.daum.net/v/20160118115304017","title":"[2030은 지금' 대한민국 엑소더스'] \"지금 당장 이민契 의향있다\"45%","cpKorName":"헤럴드경제","summary":"목돈 만들고 정보 공유삶의질 높은 북유럽·호주선호준비기간은 1년~3년 많아목표금액은 대부분 1억~3억미만 서울 소재 중견기업에 다니고 있는 A(30) 씨는 최근 블로그 활동을 통해 알게 된 4명과 함께 ‘이민계(移民契)’를 만들었다. “향후 5년동안 돈 5억원을 모으는 게 목표”라고 밝힌 A 씨는 목표에 도달하면 뉴질랜드로 이민을 떠날 계획이다. 그는 현지","regDt":"20160118115304","importantYn":"Y","imageUrl":"http://t1.daumcdn.net/news/201601/18/ned/20160118115305562mgkj.jpg","ucccount":258,"category":"society"},{"newsId":"20160118181526086","url":"http://v.media.daum.net/v/20160118181526086","title":"아파트 배관함서 실탄 72발, 수류탄 장약 106개 발견(종합)","cpKorName":"연합뉴스","summary":"관계기관 \"대공용의점은 없는듯\" (부산=연합뉴스) 김재홍 기자 = 아파트 배관함에서 군용 실탄과 연습용 수류탄 장약이 발견돼 경찰과 관계기관이 조사에 나섰다. 부산 금정경찰서에 따르면 18일 오전 10시17분 부산 금정구의 한 아파트 19층 배관함에서 5.56㎜ 실탄 72발과 연습용 수류탄 장약 106개가 발견됐다. 실탄과 장약은 각각 종이 박스에 담긴","regDt":"20160118181526","importantYn":"Y","imageUrl":"http://t1.daumcdn.net/news/201601/18/yonhap/20160118161709512ypdy.jpg","ucccount":258,"category":"society"},{"newsId":"20160118180224621","url":"http://v.media.daum.net/v/20160118180224621","title":"시신훼손 아버지 \"나도 체벌받았다\"..학대의 대물림","cpKorName":"연합뉴스","summary":"\"체벌 받다가 다친 적도 있지만 병원 간 적 없어\" (인천=연합뉴스) 강종구 최은지 기자 = 아들의 시신을 훼손한 30대 남성이 자신도 어머니에게 심한 체벌을 자주 받았다고 주장, 자녀 학대가 대물림됐을 것이라는    추측을 낳고 있다. 2012년 초등학생 1학년 아들 A군의 시신을 심하게 훼손해 냉동보관한 혐의로 구속된 B(34)씨는 경찰의 범행심리분석","regDt":"20160118180224","importantYn":"Y","imageUrl":"http://t1.daumcdn.net/news/201601/18/yonhap/20160118180223059crgt.jpg","ucccount":251,"category":"society"},{"newsId":"20160118172044981","url":"http://v.media.daum.net/v/20160118172044981","title":"두 野 '국부론' 연장전..\"국보위 참여\" vs \"진부한 뉴라이트\"","cpKorName":"연합뉴스","summary":"4·19 단체 국민의당 창준위 항의방문, 사과 요구 (서울=연합뉴스) 박수윤 기자 = '국민의당'(가칭) 한상진 공동 창당준비위원장의 '이승만 국부(國父) 발언'을 두고 더불어민주당(이하 더민주)과 국민의당 간 신경전이 고조되고 있다. 한 위원장은 18일 서울 마포 창준위 사무실에서 열린 확대 기획조정회의에서 자신의 '국부 발언'을 비판한 더민주 김종인 선","regDt":"20160118172044","importantYn":"Y","imageUrl":"http://t1.daumcdn.net/news/201601/18/yonhap/20160118172042622ejbt.jpg","ucccount":243,"category":"politics"},{"newsId":"20160118173102360","url":"http://v.media.daum.net/v/20160118173102360","title":"류준열 측 \"무분별한 루머 확산..법적 강력 대응할 것\"","cpKorName":"뉴스엔","summary":"류준열 소속사 측이 루머에 강력히 대응할 것임을 밝혔다. 1월 18일 배우 류준열 공식 페이스북에는 \"안녕하세요. 씨제스 엔터테인먼트 입니다\"라는 글이 게재됐다. 소속사 측은 \"드라마 '응답하라 1988'을 통해 배우 류준열에 보내주신 응원과 사랑에 감사 드립니다\"며 \"그러나 최근 류준열에 관련해 확인되지 않은 내용으로 작성된 허위사실과 루머들이 온라인에","regDt":"20160118173102","importantYn":"N","imageUrl":"http://t1.daumcdn.net/news/201601/18/newsen/20160118173100596cdon.jpg","ucccount":242,"category":"entertain"},{"newsId":"20160118171212667","url":"http://v.media.daum.net/v/20160118171212667","title":"레이양 측 \"진료기록 해명자료..법적대응 검토 중\" [공식입장]","cpKorName":"스포츠동아","summary":"[동아닷컴] 레이양 측 “진료기록 해명자료…법적대응 검토 중” [공식입장] 헬스트레이너 겸 방송인 레이양(30·양민화) 측이 과거 진료기록을 요청한 사실에 대해 공식입장을 밝혔다. 레이양의 소속사 토비스미디어 대표는 18일 오후 동아닷컴에 “최근 악성댓글에 시달리는 레이양이 해명을 위해 부산의 한 병원에 진료기록을 요청한 상태다. 현재 촬영 중인 관계로","regDt":"20160118171212","importantYn":"Y","imageUrl":"http://t1.daumcdn.net/news/201601/18/sportsdonga/20160118171211654unne.jpg","ucccount":237,"category":"entertain"},{"newsId":"20160118114355449","url":"http://v.media.daum.net/v/20160118114355449","title":"서정희 \"前남편 서세원 원망 안해, 잘 살았으면\"(인터뷰③)","cpKorName":"스타뉴스","summary":"[스타뉴스 윤성열 기자] 서정희 -인터뷰②에 이어서 -지금 행복한 것은 뭔가요. ▶저를 찾아주는 분들이 있다는 게 좋죠. 사람이 너무 그리웠어요. 지금은 감사해요. 같이 일하자는 얘기도 여러 군데에서 많이 들어와요. 제가 최고점을 찍었을 때도 이렇게 많이 연락을 못 받아봤어요. 19살 이후 이런 반응은 처음이에요. -결혼을 앞둔 분들에게 조언해주고","regDt":"20160118114355","importantYn":"Y","imageUrl":"http://t1.daumcdn.net/news/201601/18/starnews/20160118114354437elgk.jpg","ucccount":236,"category":"entertain"},{"newsId":"20160118175747377","url":"http://v.media.daum.net/v/20160118175747377","title":"최재성 \"새 술은 새 부대에..선대위 출발만 남아\"","cpKorName":"뉴시스","summary":"총선기획단장직 거론? 내 역할 여기까지盧 전 대통령 욕보여선 안돼…그것이 혁신의 완성 【서울=뉴시스】전혜정 기자 = 더불어민주당 최재성 총무본부장은 18일 \"새 술은 새 부대에 담아야 한다\"며 \"'김종인 선대위'의 출발은 새로움의 시작\"이라고 강조했다. 최 본부장은 이날 오후 자신의 페이스북을 통해 이 같이 말했다. 최 본부장은 \"우리당의 새로운 체제가 완","regDt":"20160118175747","importantYn":"Y","imageUrl":"http://t1.daumcdn.net/news/201512/17/newsis/20151217113421013uwuu.jpg","ucccount":232,"category":"politics"},{"newsId":"20160118093738903","url":"http://v.media.daum.net/v/20160118093738903","title":"안철수 \"무조건 '뭉치면 산다'식이면 다 죽어\"","cpKorName":"뉴시스","summary":"\"야권분열 안 된다는 인식 때문에 참담한 상황\" 【서울=뉴시스】박주연 기자 = 더불어민주당 안철수 의원은 18일 야권 분열 우려에 대해 \"무조건 '뭉치면 산다'는 식으로는 다 죽는다\"고 잘라말했다. 안 의원은 이날 오전 마포 일신빌딩 당사에서 열린 확대기획조정회의에서 \"더불어민주당 문재인 대표가 야권분열은 새누리당이 원하는 것이라고 말했는데, 바로 그런","regDt":"20160118093738","importantYn":"Y","imageUrl":"http://t1.daumcdn.net/news/201601/17/newsis/20160117105621157ozpq.jpg","ucccount":229,"category":"politics"},{"newsId":"20160118063604732","url":"http://v.media.daum.net/v/20160118063604732","title":"[단독]'월드컵터널 가방 시신' 유력 용의자, '남친'숨진 채 발견(종합)","cpKorName":"노컷뉴스","summary":"서울 월드컵터널 근처 풀숲에서 20대 초반 여성이 숨진 채 가방에 담겨 발견된 가운데 사건의 유력한 용의자인 남자친구가 집에서 숨진 채 발견됐다. 경찰은 유력 용의자가 숨졌지만 사건 전반의 의혹을 낱낱이 수사한다는 방침이다. 18일 서울지방경찰청과 경기도 안성경찰서 등에 따르면 피해 여성 김모(23)씨의 유족과 주변 관계자, 지인 등에 대한 수사를 진행","regDt":"20160118063604","importantYn":"Y","imageUrl":"http://t1.daumcdn.net/news/201601/18/nocut/20160118063603455lkjc.jpg","ucccount":229,"category":"society"},{"newsId":"20160118201707912","url":"http://v.media.daum.net/v/20160118201707912","title":"'박 대통령 명예훼손 무죄' 산케이 전 서울지국장 수기 출판","cpKorName":"연합뉴스","summary":"(도쿄=연합뉴스) 박근혜 대통령의 명예를 훼손한 혐의로 기소됐다가 1심에서 무죄 판결이 확정된 가토 다쓰야(加藤達也) 산케이(産經)신문 전 서울지국장이 관련 경험을 수기로 펴낸다고 산케이신문이 18일 밝혔다. 사진은 산케이신문이 공개한 가토 전 지국장의 수기 표지 모습. <<산케이신문 홈페이지 캡처>> 2016.1.18 sewonlee@yna.co.kr (","regDt":"20160118201707","importantYn":"Y","imageUrl":"http://t1.daumcdn.net/news/201601/18/yonhap/20160118201706388xqvm.jpg","ucccount":227,"category":"foreign"},{"newsId":"20160118210014889","url":"http://v.media.daum.net/v/20160118210014889","title":"[날씨] 강력 한파에 전국 '꽁꽁', 내일까지 충청·호남 폭설","cpKorName":"MBC","summary":"[뉴스데스크]강력한 한파에 전국이 급격히 얼어붙고 있습니다. 내일 출근길 벌써부터 걱정이 앞서는데요. 서울이 모스크바보다 더 추워서 내일 아침 영하 14도까지 내려가겠습니다. 대관령도 영하 19도까지 떨어지겠는데요. 실제 거리에서 느껴지는 추위의 강도는 칼바람의 세기에 따라 달라집니다. 내일 서울의 체감온도가 영하 25도, 대관령은 영하 35도에 육박하겠습","regDt":"20160118210014","importantYn":"Y","imageUrl":"http://t1.daumcdn.net/news/201601/18/imbc/20160118210012740ogzq.jpg","ucccount":224,"category":"economic"},{"newsId":"20160118104432088","url":"http://v.media.daum.net/v/20160118104432088","title":"\"쯔위가 134만명 투표 참여시켰다\"..청년층 차이잉원에 몰표","cpKorName":"연합뉴스","summary":"(상하이=연합뉴스) 정주호 특파원 = 한국 걸그룹 트와이스의 멤버 쯔위(周子瑜·17) 사태가 대만의 젊은층 134만표의 향방을 결정했다는 조사결과가 나왔다. 18일 홍콩 사우스차이나모닝포스트(SCMP)에 따르면 대만 양안정책협회의 온라인 조사 결과 134만명의 청년층이 '쯔위 사건'의 영향으로 투표 참여를 결정했거나 투표의향을 바꾼 것으로 나타났다. 차이","regDt":"20160118104432","importantYn":"Y","imageUrl":"http://t1.daumcdn.net/news/201601/18/yonhap/20160118104431141hlzm.jpg","ucccount":223,"category":"foreign"},{"newsId":"20160118204512544","url":"http://v.media.daum.net/v/20160118204512544","title":"MB 정부 고위직 '계좌 추적'..\"무혐의 종결\"","cpKorName":"SBS","summary":"<앵커> 이명박 정부에서 고위직을 지낸 인사들이 검찰에 집단으로 반발하고 나섰습니다. 검찰이 자신들의 계좌를 조회한 사실을 뒤늦게 통보받았기 때문입니다. 계좌 추적을 부인하던 검찰은 뒤늦게 사실을 시인했습니다. 보도에 김수형 기자입니다. <기자> 오늘(18일) 오후 이명박 정부에서 장·차관과 청와대 수석을 지낸 고위직 인사 10여 명이 이 전 대통령 사무실","regDt":"20160118204512","importantYn":"Y","imageUrl":"http://t1.daumcdn.net/news/201601/18/sbsi/20160118204510819szsd.jpg","ucccount":213,"category":"society"},{"newsId":"20160118121701013","url":"http://v.media.daum.net/v/20160118121701013","title":"알바노조 \"노동청 진정 넣은 알바 99% 근로감독관에 불만\"","cpKorName":"뉴스1","summary":"(서울=뉴스1) 윤수희 기자,이주성 기자 = 아르바이트 과정 중 임금체불 등의 불합리한 대우를 당해 노동청에 진정을 넣을 경우 이를 해결하는 근로감독관이 고용주에 유리하게 일을 처리한다는 주장이 나왔다. 알바노조는 18일 서울 중구 고용노동청 앞에서 기자회견을 열고 \"노동청에 진정을 넣어본 적 있는 아르바이트 노동자 100명을 대상으로 설문조사를 실시한","regDt":"20160118121701","importantYn":"Y","imageUrl":"http://t1.daumcdn.net/news/201601/18/NEWS1/20160118115109638fmls.jpg","ucccount":213,"category":"society"},{"newsId":"20160118224100690","url":"http://v.media.daum.net/v/20160118224100690","title":"[탐사플러스] 유흥업소 여종업원 '의문사'..증언으로 본 사건의 재구성","cpKorName":"JTBC","summary":"[앵커] 지난해 말 전남 여수의 한 유흥업소에서 30대 여종업원이 숨졌습니다. 경찰이 최초로 판단한 사인은 과음으로 인한 질식사였습니다. 하지만 이 여성은 업주로부터 상습 폭행을 당했고 사건 당일에 쓰러지기 직전까지 심하게 매를 맞았다는 진술을 저희 취재팀이 확보했습니다. 또 문제가 되는 것이 있는데요. 숨진 여성을 포함한 업소 여성들은 성매수 장부를 가","regDt":"20160118224100","importantYn":"Y","imageUrl":"http://t1.daumcdn.net/news/201601/18/JTBC/20160118224057698xjqs.jpg","ucccount":213,"category":"society"},{"newsId":"20160118150148647","url":"http://v.media.daum.net/v/20160118150148647","title":"문재인 사퇴 승부는 언제..신년회견서? 광주서?(종합)","cpKorName":"뉴스1","summary":"(서울=뉴스1) 박태정 기자,박승주 기자 = 문재인 더불어민주당 대표의 사퇴 시기를 두고 정치권의 관심이 모아지고 있다. 문 대표는 선거대책위 구성 후 사퇴를 공언했지만 대표직 사퇴는 이반된 호남 민심 복구와도 연계될 수밖에 없는 만큼 시기 조율에 고심하는 모양새다. 문 대표 사퇴는 이르면 이번 주중, 늦어져도 설 연휴 이전에는 불가피하다는 게 중론이다","regDt":"20160118150148","importantYn":"Y","imageUrl":"http://t1.daumcdn.net/news/201601/18/NEWS1/20160118094605395fszj.jpg","ucccount":211,"category":"politics"},{"newsId":"20160118151335474","url":"http://v.media.daum.net/v/20160118151335474","title":"은퇴 후 100명 중 84명, \"최저생활비 마련도 어렵다\"","cpKorName":"뉴시스","summary":"은퇴와 연금계약 간 평균 10년의 공백기간 발생노후준비목적과는 무관하게 연금계약체결 '23.1%'세제적격 연금보다 세제비적격 연금보험 적극 활용해야 【서울=뉴시스】김경원 기자 = 은퇴준비자 100명 중 84명은 은퇴 후 최소생활비 마련도 어려운 것으로 나타났다. 보험개발원은 2014~2015년 은퇴준비자 1266명을 대상으로 은퇴준비 실태를 조사한 결과,","regDt":"20160118151335","importantYn":"Y","imageUrl":"http://t1.daumcdn.net/news/201601/18/newsis/20160118151334788pztt.jpg","ucccount":208,"category":"society"},{"newsId":"20160118074046517","url":"http://v.media.daum.net/v/20160118074046517","title":"'응팔' 박보검 \"여전히 지하철 애용, 사람들 못 알아봐\"[포토엔]","cpKorName":"뉴스엔","summary":"박보검이 생애 첫 팬미팅을 열었다. 박보검은 2016년 1월 16일, 공식팬카페 ‘보검복지부’와 함께 서울 KBS 아레나에서 ‘우리들의 첫 만남, 설렘’이라는 주제로 첫 팬미팅을 개최했다. 약 3500여명의 팬들과 3시간 동안 함께했다. 이번 팬미팅은 ‘개그콘서트-헬스보이’로 유명한 개그맨 이승윤이 사회를 맡았으며 1부는 팬들과 함께 소통하는 시간으로","regDt":"20160118074046","importantYn":"Y","imageUrl":"http://t1.daumcdn.net/news/201601/18/newsen/20160118074044965gcqv.jpg","ucccount":206,"category":"entertain"},{"newsId":"20160118141015212","url":"http://v.media.daum.net/v/20160118141015212","title":"'응팔' 혜리♥박보검, 애틋한 종영소감..스킨십도 척척","cpKorName":"마이데일리","summary":"[마이데일리 = 박윤진 기자] 걸그룹 걸스데이 멤버 겸 배우 혜리와 배우 박보검이 종영 소감을 밝혔다. 18일 '응답하라 1988' 공식 페이스북에는 '굿바이, 응답하라 1988' 마지막 이야기라는 제목으로 영상이 게재됐다. 영상 속 박보검은 \"시청자 여러분 정말 감사드리고요. 앞으로도 저와 덕선이\"라고 말하다 말끝을 흐렸다. 그러자 혜리는 \"왜 울어","regDt":"20160118141015","importantYn":"Y","imageUrl":"http://t1.daumcdn.net/news/201601/18/mydaily/20160118141014371uzjw.jpg","ucccount":206,"category":"entertain"},{"newsId":"20160118110541210","url":"http://v.media.daum.net/v/20160118110541210","title":"'安당' 광주·전남의원들 전진배치 '호남당·공천권' 논란","cpKorName":"뉴시스","summary":"【광주=뉴시스】배상현 기자 = 안철수 의원이 창당을 추진 중인 국민의당의 주요 보직에 더불어민주당을 탈당한 광주·전남지역 출신 국회의원들이 대거 전진배치됐다. 지역정가에서는 국민의당이 ‘호남당’ 이미지에서 벗어나지 못하고 있다는 지적과 함께, 현역 의원들의 보직 부여가 공천으로 이어질 것인가에 관심이 모아지고 있다. 18일 광주·전남지역 정가에 따르면","regDt":"20160118110541","importantYn":"Y","imageUrl":"http://t1.daumcdn.net/news/201601/11/newsis/20160111172840175xfes.jpg","ucccount":202,"category":"politics"},{"newsId":"20160118211637238","url":"http://v.media.daum.net/v/20160118211637238","title":"라미란 김성균, 무명시절 생활고 거쳐 현재 몸값 2억원대 반전(명단공개)","cpKorName":"뉴스엔","summary":"[뉴스엔 이소담 기자] 라미란 김성균이 반전 주인공이 됐다. 김성균 라미란 몸값이 1월18일 방송된 tvN '명단공개 2015'에서 공개돼 화제다. 과거 무명시절을 거쳐 단역으로 활동했던 라미란은 연봉이 1,000만 원에도 미치지 못하며 어려운 시절을 보냈다. 김성균 또한 택배기사로 일하며 연극배우 시절을 버텼다. 그랬던 라미란 김성균은 각각 '응답","regDt":"20160118211637","importantYn":"Y","imageUrl":"http://t1.daumcdn.net/news/201601/18/newsen/20160118211636632fjwe.jpg","ucccount":199,"category":"entertain"},{"newsId":"20160118105512604","url":"http://v.media.daum.net/v/20160118105512604","title":"[취재파일] 평창 조직위 살린 56살 공학도","cpKorName":"SBS","summary":"2018 평창 동계올림픽 스키 활강과 슈퍼대회전 종목이 열리는 강원도 정선 알파인 경기장이 오는 22일 오전 11시 김종덕 문화체육관광부 장관, 조양호 평창 조직위원장, 최문순 강원도지사 등 주요 인사 150여명이 참석한 가운데 현장에서 개장식을 갖습니다. 모레(20일) 국제스키연맹(FIS)의 최종 실사가 남아 있지만 FIS가 요구한 조건이 이미 모두 충족","regDt":"20160118105512","importantYn":"N","imageUrl":"http://t1.daumcdn.net/news/201601/18/sbsi/20160118105509521edxz.jpg","ucccount":198,"category":"sports"},{"newsId":"20160118164506704","url":"http://v.media.daum.net/v/20160118164506704","title":"박영선 손학규 정운찬..\"속타는 안철수\"","cpKorName":"머니투데이","summary":"[머니투데이 심재현  기자] [[the300]'김종인 역풍'에 내부잡음까지 겹쳐…더민주와 차별화 나서] '안철수 바람'이 '김종인 역풍'을 만났다. 현역의원의 잇단 탈당으로 휘청였던 더불어민주당이 김종인 선거대책위원장 영입을 계기로 발빠르게 수습에 나서면서다. 교섭단체 구성을 목전에 두고 기세를 올리던 국민의당은 내부 잡음까지 겹치면서 더민주 손학규 전","regDt":"20160118164506","importantYn":"Y","imageUrl":"http://t1.daumcdn.net/news/201601/18/moneytoday/20160118164505077ivbj.jpg","ucccount":196,"category":"politics"},{"newsId":"20160118065603889","url":"http://v.media.daum.net/v/20160118065603889","title":"'석궁테러' 피해 박홍우 대전고법원장 사의 표명","cpKorName":"연합뉴스","summary":"(서울=연합뉴스) 방현덕 기자 = '석궁테러' 사건의 피해자인 박홍우(64·사법연수원 12기) 대전고법원장이 사의를 표명한 것으로 알려졌다. 18일 법조계에 따르면 박 원장은 최근 대법원에 2월 인사 때 법원을 떠나겠다는 의사를 표명했다. 1982년 임관한 지 34년 만이다. 박 원장은 2007년 서울고법 민사2부 재판장 시절 김명호 성균관대 전 조교수의","regDt":"20160118065603","importantYn":"Y","imageUrl":"http://t1.daumcdn.net/news/201601/18/yonhap/20160118065602259adpy.jpg","ucccount":193,"category":"society"},{"newsId":"20160118181434031","url":"http://v.media.daum.net/v/20160118181434031","title":"\"IS, 지난달 전투원 월급 절반으로 삭감했다\"","cpKorName":"연합뉴스","summary":"(이스탄불=연합뉴스) 김준억 특파원 = 수니파 무장조직 '이슬람국가'(IS)가 지난달 전투원들의 월급을 절반으로 삭감했다는 주장이 나왔다. 이슬람 극단주의 조직 전문가인 아이멘 알타미미는 18일(현지시간) 트위터를 통해 IS가 전투원의 월급을 50% 삭감하기로 결정했다는 문서를 입수했다고 밝혔다. 알타미미가 영어로 번역한 이 문서에 따르면 IS는 \"이슬람국","regDt":"20160118181434","importantYn":"Y","imageUrl":"http://t1.daumcdn.net/news/201601/18/yonhap/20160118181433799xhoz.jpg","ucccount":191,"category":"foreign"},{"newsId":"20160118182303405","url":"http://v.media.daum.net/v/20160118182303405","title":"수퍼리치 1%의 재산이 나머지 99%의 재산 보다 많아","cpKorName":"중앙일보","summary":"전세계 상위 1% 부자가 보유한 재산이 나머지 99%의 재산을 넘어섰다. BBC는 18일(현지시간) 국제구호기구 옥스팜이 크레디트스위스의 데이터를 인용해 작성한 보고서를 인용, 보도했다. 옥스팜은 20일 스위스에서 열리는 세계경제포럼(WEF·다보스포럼)에서 이런 불평등 문제에 대한 대책을 논의해야 한다고 촉구했다. 지난해 10월 자료에 기반한 옥스팜의 보고","regDt":"20160118182303","importantYn":"Y","imageUrl":"http://t1.daumcdn.net/news/201601/18/joongang/20160118182302358rckx.jpg","ucccount":189,"category":"economic"}]}